akashic_records/__init__.py
akashic_records/_meta/__init__.py
akashic_records/_meta/compiler.py
akashic_records/_meta/dynamic_function.py
akashic_records/_meta/errors.py
akashic_records/_meta/injector.py
akashic_records-0.3.0.dist-info/LICENSE
akashic_records-0.3.0.dist-info/WHEEL
akashic_records-0.3.0.dist-info/METADATA
akashic_records-0.3.0.dist-info/RECORD
