Metadata-Version: 2.1
Name: akashic-records
Version: 0.3.0
Summary: Generate and execute python code via OpenAI code completion
Home-page: https://github.com/buckley-w-david/akashic_records
License: MIT
Author: David Buckley
Author-email: david@davidbuckley.ca
Requires-Python: >=3.10,<4.0
Classifier: License :: OSI Approved :: MIT License
Classifier: Programming Language :: Python :: 3
Classifier: Programming Language :: Python :: 3.10
Requires-Dist: openai (>=0.27.2,<0.28.0)
Requires-Dist: sorcery (>=0.2.2,<0.3.0)
Project-URL: Documentation, https://github.com/buckley-w-david/akashic_records#usage
Project-URL: Repository, https://github.com/buckley-w-david/akashic_records
